README.md
setup.py
pyvalidators/__init__.py
pyvalidators/areacode.py
pyvalidators/base.py
pyvalidators/email.py
pyvalidators/idcard.py
pyvalidators/ipaddr.py
pyvalidators/phone.py
pyvalidators/url.py
pyvalidators.egg-info/PKG-INFO
pyvalidators.egg-info/SOURCES.txt
pyvalidators.egg-info/dependency_links.txt
pyvalidators.egg-info/not-zip-safe
pyvalidators.egg-info/top_level.txt
tests/__init__.py
tests/test_email.py
tests/test_ipaddr.py
tests/test_phone.py
tests/test_simple.py
tests/test_url.py