Metadata-Version: 1.0
Name: pyvalidators
Version: 0.1.7
Summary: Common validators component.
Home-page: https://github.com/istommao/pyvalidators
Author: silence
Author-email: istommao@gmail.com
License: UNKNOWN
Keywords: pyvalidators is a common validators component!
Platform: UNKNOWN
